strique_proto_schema
