Metadata-Version: 2.4
Name: strique-proto-schema
Version: 32.1.16
Summary: API contracts and Data Transfer Objects (DTO) in the form of Protocol Buffers for Strique binaries.
Requires-Python: >=3.7
Requires-Dist: requests
Requires-Dist: grpcio
Requires-Dist: grpcio-tools
Requires-Dist: mypy-protobuf==3.4.0
